arcade_cli/__init__.py
arcade_cli/__main__.py
arcade_cli/arcade.py
arcade_cli/cli.py
arcade_cli/draw.py
arcade_cli-0.3.2.dist-info/entry_points.txt
arcade_cli-0.3.2.dist-info/WHEEL
arcade_cli-0.3.2.dist-info/METADATA
arcade_cli-0.3.2.dist-info/RECORD
